pulse_lucide/__init__.py
pulse_lucide/__init__.pyi
pulse_lucide/props.py
pulse_lucide/py.typed
pulse_lucide-0.546.1.dist-info/WHEEL
pulse_lucide-0.546.1.dist-info/METADATA
pulse_lucide-0.546.1.dist-info/RECORD
