Metadata-Version: 2.3
Name: pulse-lucide
Version: 0.546.1
Summary: Lucide icons for the Pulse framework
Author: Erwin Kuhn
Author-email: Erwin Kuhn <erwin.kuhn@protonmail.com>
Requires-Dist: pulse-framework
Requires-Python: >=3.11
